[
    {
        "code": "012",
        "name": "Cafer Tuzak"
    },
    {
        "code": "013",
        "name": "Ali Alacadağlıer"
    },
    {
        "code": "011",
        "name": "Hasan Öztürk"
    },
    {
        "code": "031",
        "name": "Onur Öner"
    },
    {
        "code": "052",
        "name": "Berkay Arslan"
    },
    {
        "code": "051",
        "name": "Mustafa Yurttav"
    },
    {
        "code": "063",
        "name": "Duran Şağban"
    },
    {
        "code": "062",
        "name": "Emre Kıran"
    },
    {
        "code": "061",
        "name": "İbrahim Arslan"
    },
    {
        "code": "064",
        "name": "Rahman Yiğit Çelikkol"
    },
    {
        "code": "071",
        "name": "Harun Karık"
    },
    {
        "code": "073",
        "name": "İsmail Taha Us"
    },
    {
        "code": "072",
        "name": "Tuncay Özel"
    },
    {
        "code": "101",
        "name": "Hüseyin Benli"
    },
    {
        "code": "111",
        "name": "Nazım Gülfidan"
    },
    {
        "code": "163",
        "name": "Harun Kürşat Kölege"
    },
    {
        "code": "162",
        "name": "İhsan Kolukısa"
    },
    {
        "code": "161",
        "name": "Raşit Çiçek"
    },
    {
        "code": "171",
        "name": "Mehmet Kir"
    },
    {
        "code": "191",
        "name": "Mustafa Özbek"
    },
    {
        "code": "201",
        "name": "Süleyman Kamil Ünal"
    },
    {
        "code": "231",
        "name": "Yusuf Ulaş"
    },
    {
        "code": "241",
        "name": "Önder Bayrak"
    },
    {
        "code": "251",
        "name": "Harun Bayrak"
    },
    {
        "code": "252",
        "name": "Mehmet Erkan Tanıyan"
    },
    {
        "code": "261",
        "name": "Hakan Bahar"
    },
    {
        "code": "271",
        "name": "Rahmi Demir"
    },
    {
        "code": "311",
        "name": "Yusuf Çetin"
    },
    {
        "code": "321",
        "name": "Ahmet Göksel Gelir"
    },
    {
        "code": "322",
        "name": "Rıza Konak"
    },
    {
        "code": "343",
        "name": "Lokman Tok"
    },
    {
        "code": "346",
        "name": "Nusret Daloğlu"
    },
    {
        "code": "342",
        "name": "Sezer Polat"
    },
    {
        "code": "345",
        "name": "Hasan Ekşi"
    },
    {
        "code": "343",
        "name": "Nuran Keskin"
    },
    {
        "code": "344",
        "name": "Ömer Ergün"
    },
    {
        "code": "347",
        "name": "Galip Zafer Eroğlu"
    },
    {
        "code": "348",
        "name": "Abbas Özdemir"
    },
    {
        "code": "351",
        "name": "Musa Toplu"
    },
    {
        "code": "352",
        "name": "Yasin Altı"
    },
    {
        "code": "461",
        "name": "Ahmet Taş"
    },
    {
        "code": "462",
        "name": "Nadir Aytemiz"
    },
    {
        "code": "361",
        "name": "Mustafa Yıldırımçakar"
    },
    {
        "code": "381",
        "name": "Serkan Yeni"
    },
    {
        "code": "382",
        "name": "Yusuf Öner"
    },
    {
        "code": "383",
        "name": "Mustafa Sağır"
    },
    {
        "code": "384",
        "name": "Eren Kevek"
    },
    {
        "code": "423",
        "name": "Akif Doğan"
    },
    {
        "code": "421",
        "name": "Yunus Açık"
    },
    {
        "code": "422",
        "name": "Kadir Demir"
    },
    {
        "code": "431",
        "name": "Samed Atay"
    },
    {
        "code": "441",
        "name": "Ahmet İnan"
    },
    {
        "code": "452",
        "name": "Ahmet Karakuş"
    },
    {
        "code": "451",
        "name": "Yusuf Caner Yağcı"
    },
    {
        "code": "471",
        "name": "Kamile Coşkun"
    },
    {
        "code": "332",
        "name": "Celalettin Göktaş"
    },
    {
        "code": "331",
        "name": "Muzaffer Yeşilkuş"
    },
    {
        "code": "521",
        "name": "Halil Kavak"
    },
    {
        "code": "531",
        "name": "Oğuz Kılıç"
    },
    {
        "code": "541",
        "name": "Özgür Yan"
    },
    {
        "code": "542",
        "name": "Sezgin Uğur"
    },
    {
        "code": "551",
        "name": "Ömer Faruk Hızarcı"
    },
    {
        "code": "552",
        "name": "Serdar Yokarıbaş"
    },
    {
        "code": "582",
        "name": "Metehan Kartal"
    },
    {
        "code": "581",
        "name": "Tolgahan Kartal"
    },
    {
        "code": "601",
        "name": "Emre Şaşmaz"
    },
    {
        "code": "611",
        "name": "Serhat Ergenç"
    },
    {
        "code": "651",
        "name": "Emircan Atacan"
    }
]